hello.v
`timescale 1ns / 1ps

module pipe_stage #(
    parameter WIDTH=8
) (
    input clk,
    input i_reset_n,

    input [WIDTH-1:0] i_data,
    input i_vld,
    output o_rdy,

    output [WIDTH-1:0] o_data,
    output o_vld,
    input i_rdy
);

    //initial $monitor("Somebody changed my clk to %d", clk);

    wire rd_sig = o_vld && i_rdy;
    wire wr_sig = i_vld && o_rdy;
    
    reg [1:0][WIDTH-1:0] storage;
    reg [1:0]            storage_vld;
    wire [1:0]           storage_vld_nxt;
    
    
    generate 
    for (genvar i = 0; i < 2; i = i + 1) begin
        always @(posedge clk) begin
            if (!i_reset_n) begin
                storage[i] <= {WIDTH{1'b0}};
            end else if (wr_sig && (wr_ptr == i[0])) begin
                storage[i] <= i_data;
            end
        end

        always @(posedge clk) begin
            if (!i_reset_n || (rd_sig && (rd_ptr==i[0]))) begin
                storage_vld[i] <= 1'b0;
            end else if (wr_sig && wr_ptr==i[0]) begin
                storage_vld[i] <= 1'b1;
            end
        end

        // TODO: We could put some kind of verilog behavioural
        // assert here that we don't read and write to the same
        // slot, but we will do it in Lua instead.
        // - IMO it's better to avoid putting sim-only code in
        //   your RTL
        // - Ultimately I'm trying to test the Lua interface
    end 
    endgenerate

    reg rd_ptr; wire rd_ptr_nxt;
    reg wr_ptr; wire wr_ptr_nxt;

    always @(posedge clk) begin
        if (!i_reset_n) begin
            rd_ptr <= 0;
            wr_ptr <= 0;
        end else begin
            rd_ptr <= rd_ptr_nxt;
            wr_ptr <= wr_ptr_nxt;
        end
    end

    assign rd_ptr_nxt = rd_ptr ^ rd_sig;
    assign wr_ptr_nxt = wr_ptr ^ wr_sig;
    
    assign o_data = storage[rd_ptr];
    assign o_vld = storage_vld[rd_ptr];
    assign o_rdy = !storage_vld[wr_ptr];
endmodule

module counter # (
    parameter WIDTH=8
) (
    input clk,
    input i_reset_n,

    input i_en,
    output [WIDTH-1:0] o_cnt
);
    reg [WIDTH-1:0] cnt;

    always @(posedge clk) begin
        if (!i_reset_n) begin
            cnt <= {WIDTH{1'b0}};
        end else begin
            cnt <= cnt + 1'b1; //Should be unsigned... right?
                               //Gotta check the gotchas...
        end
    end

    assign o_cnt = cnt;
endmodule



module tb;

    //Simple thing to test value-change callbacks
    reg thing = 0;
    always #2 thing = ~thing;
    
    pipe_stage DUT();


    //Simple thing to test those tricky time-related callbacks
    //for the different phases of the verilog event queue
    
    //Hmm... it might be a bad sign that it's still more
    //convenient to make certain testbench inputs in verilog...
    //Maybe if I had a better support library it would be
    //nicer in lua?
    reg tb_clk = 0;
    always #5 tb_clk = ~tb_clk;
    reg tb_rstn = 0;
    initial #10 tb_rstn = 1;
    wire [7:0] cnt;
    counter u_cnt(
        .clk(tb_clk),
        .i_reset_n(tb_rstn),
        .i_en(1'b1),
        .o_cnt(cnt)
    );

    //Simple thing to test events
    event my_ev; 
    always @(my_ev) begin
        $display("Someone triggered an event!\n");
    end
    
    initial begin
        // "dump" is such an ugly word :-/
        $dumpfile("sim_out.vcd");
        $dumpvars;
        $dumpon;
        $dumplimit(10240);
        $display("Begin typing lua code. (Sorry, no autocomplete!)");
        $lua_repl;
        #40
        $display("Goodbye");
        $finish;
    end

endmodule

sim_out.vcd
$date
	Sat May  7 10:14:11 2022
$end
$version
	Icarus Verilog
$end
$timescale
	1ps
$end
$scope module tb $end
$var event 1 ! my_ev $end
$var wire 8 " cnt [7:0] $end
$var reg 1 # tb_clk $end
$var reg 1 $ tb_rstn $end
$var reg 1 % thing $end
$scope module DUT $end
$var wire 1 & clk $end
$var wire 8 ' i_data [7:0] $end
$var wire 1 ( i_rdy $end
$var wire 1 ) i_reset_n $end
$var wire 1 * i_vld $end
$var wire 1 + rd_ptr_nxt $end
$var wire 1 , rd_sig $end
$var wire 1 - wr_ptr_nxt $end
$var wire 1 . wr_sig $end
$var wire 1 / o_vld $end
$var wire 1 0 o_rdy $end
$var wire 8 1 o_data [7:0] $end
$var reg 1 2 rd_ptr $end
$var reg 16 3 storage [15:0] $end
$var reg 2 4 storage_vld [1:0] $end
$var reg 1 5 wr_ptr $end
$scope begin genblk1[0] $end
$upscope $end
$scope begin genblk1[1] $end
$upscope $end
$upscope $end
$scope module u_cnt $end
$var wire 1 # clk $end
$var wire 1 6 i_en $end
$var wire 1 $ i_reset_n $end
$var wire 8 7 o_cnt [7:0] $end
$var reg 8 8 cnt [7:0] $end
$upscope $end
$upscope $end
$enddefinitions $end
#0
$dumpvars
bx 8
bx 7
16
x5
bx 4
bx 3
x2
bx 1
x0
x/
0.
x-
x,
x+
0*
0)
z(
bz '
0&
0%
0$
0#
bx "
1!
$end
#100
0+
0,
0-
b0 1
0/
10
b0 3
b0 4
05
02
1&
#200
0&
#300
1&
#400
0&
#500
1&
#600
0&
#700
1&
#800
0&
#900
1&
#1000
0&
1)
#1100
1-
1.
0(
1&
1*
b1 '
#1200
0&
#1300
0.
b10 '
0*
0(
1-
b1 1
b1 3
1/
b1 4
15
1&
#1400
0&
#1500
b10 '
0*
0(
1&
#1600
0&
#1700
0-
1+
1.
1,
b10 '
1*
1(
1&
#1800
0&
#1900
0.
b11 '
0*
1(
0-
0+
05
b10 1
12
10
b1000000001 3
1/
b10 4
1&
#2000
0&
1%
#2100
1-
1.
b11 '
1*
1(
0,
0+
b0 4
b1 1
0/
02
1&
#2200
0&
#2300
0.
b100 '
0*
1(
1+
1-
1,
15
1/
10
b1 4
b11 1
b1000000011 3
1&
#2400
0&
#2500
b100 '
0*
1(
0,
1+
b0 4
b10 1
0/
12
1&
#2600
0&
#2700
0-
1.
b100 '
1*
1(
1&
#2800
0&
#2900
b101 '
1*
1(
0+
1,
1-
b100 1
b10000000011 3
1/
b10 4
05
1&
#3000
0&
#3100
0.
0,
b110 '
0*
0(
1-
0+
15
b101 1
02
1/
10
b1 4
b10000000101 3
1&
#3200
0&
#3300
1+
1,
b110 '
0*
1(
1&
#3400
0&
#3500
0-
1.
b110 '
1*
0(
0,
b100 1
12
0/
b0 4
1&
#3600
0&
#3700
0+
0.
1,
b111 '
0*
1(
0-
b110 1
b11000000101 3
1/
b10 4
05
1&
#3800
0&
#3900
b111 '
0*
0(
0,
b101 1
02
0/
b0 4
1&
#4000
0&
0%
#4100
b111 '
0*
1(
1&
#4200
0&
#4300
1-
1.
b111 '
1*
1(
1&
#4400
0&
#4500
0.
b1000 '
0*
1(
1+
1,
1-
b111 1
b11000000111 3
1/
b1 4
15
1&
#4600
0&
#4700
0-
1.
b1000 '
1*
0(
0,
b110 1
12
0/
b0 4
1&
#4800
0&
#4900
0+
0.
1,
b1001 '
0*
1(
0-
b1000 1
b100000000111 3
1/
b10 4
05
1&
#5000
b0 "
b0 7
b0 8
0&
1#
#5100
1-
1.
b1001 '
1*
1(
0,
b111 1
02
0/
b0 4
1&
#5200
0&
#5300
b1010 '
1*
1(
1+
1,
0-
b1001 1
b100000001001 3
1/
b1 4
15
1&
#5400
0&
#5500
0.
0,
b1011 '
0*
0(
0-
1+
05
b1010 1
12
10
b101000001001 3
1/
b10 4
1&
#5600
0&
#5700
1-
1.
b1011 '
1*
0(
1&
#5800
0&
#5900
0+
1,
b1100 '
0*
1(
0.
15
00
b11 4
b101000001011 3
1&
#6000
0&
1%
#6100
0-
1.
0,
b1100 '
1*
0(
0+
10
b1 4
b1011 1
02
1&
#6200
0&
#6300
b1101 '
0*
0(
0.
05
00
b11 4
b110000001011 3
1&
#6400
0&
#6500
b1101 '
0*
0(
1&
#6600
0&
#6700
1+
1,
b1101 '
1*
1(
1&
#6800
0&
#6900
0,
b1101 '
1*
0(
1-
1.
1+
10
b10 4
b1100 1
12
1&
#7000
0&
#7100
b1110 '
0*
0(
0.
15
00
b11 4
b110000001101 3
1&
#7200
0&
#7300
b1110 '
0*
0(
1&
#7400
0&
#7500
b1110 '
1*
0(
1&
#7600
0&
#7700
0+
1,
b1110 '
1*
1(
1&
#7800
0&
#7900
0,
b1110 '
1*
0(
0-
0+
1.
b1101 1
02
1/
10
b1 4
1&
#8000
0&
0%
#8100
1+
1,
b1111 '
0*
1(
0.
0-
b111000001101 3
b11 4
00
05
1&
#8200
0&
#8300
b1111 '
0*
1(
0+
b1110 1
12
1/
10
b10 4
1&
#8400
0&
#8500
1-
1.
b1111 '
1*
1(
0,
0+
b0 4
b1101 1
0/
02
1&
#8600
0&
#8700
0.
b10000 '
0*
0(
0+
1-
0,
15
1/
10
b1 4
b1111 1
b111000001111 3
1&
#8800
0&
#8900
0-
1.
b10000 '
1*
0(
1&
#9000
0&
#9100
b10001 '
0*
0(
0.
05
00
b11 4
b1000000001111 3
1&
#9200
0&
#9300
b10001 '
0*
0(
1&
#9400
0&
#9500
b10001 '
0*
0(
1&
#9600
0&
#9700
1+
1,
b10001 '
1*
1(
1&
#9800
0&
#9900
b10001 '
1*
1(
1-
0+
1.
b10000 1
12
1/
10
b10 4
1&
#10000
0&
1%
0#
1$
#10100
0.
b10010 '
0*
1(
1-
1+
b1000000010001 3
b1 4
10
15
b10001 1
1/
02
1&
#10200
0&
#10300
0-
1.
b10010 '
1*
1(
0,
b10000 1
12
0/
b0 4
1&
#10400
0&
#10500
0.
b10011 '
0*
0(
1+
0,
0-
b10010 1
b1001000010001 3
1/
b10 4
05
1&
#10600
0&
#10700
1-
1.
b10011 '
1*
0(
1&
#10800
0&
#10900
0+
1,
b10100 '
0*
1(
0.
1-
b1001000010011 3
b11 4
00
15
1&
#11000
0&
#11100
0-
1.
b10100 '
1*
1(
1+
b10011 1
02
1/
10
b1 4
1&
#11200
0&
#11300
0.
b10101 '
0*
1(
0-
0+
b1010000010011 3
b10 4
10
05
b10100 1
1/
12
1&
#11400
0&
#11500
1-
1.
b10101 '
1*
0(
0,
b10011 1
02
0/
b0 4
1&
#11600
0&
#11700
1+
0.
1,
b10110 '
0*
1(
1-
b10101 1
b1010000010101 3
1/
b1 4
15
1&
#11800
0&
#11900
b10110 '
0*
0(
0,
b10100 1
12
0/
b0 4
1&
#12000
0&
0%
#12100
b10110 '
0*
1(
1&
#12200
0&
#12300
0-
1.
b10110 '
1*
0(
1&
#12400
0&
#12500
0+
0.
1,
b10111 '
0*
1(
0-
b10110 1
b1011000010101 3
1/
b10 4
05
1&
#12600
0&
#12700
1-
1.
b10111 '
1*
1(
0,
b10101 1
02
0/
b0 4
1&
#12800
0&
#12900
0.
b11000 '
0*
0(
0+
0,
1-
b10111 1
b1011000010111 3
1/
b1 4
15
1&
#13000
0&
#13100
1+
1,
b11000 '
0*
1(
1&
#13200
0&
#13300
b11000 '
0*
1(
0,
1+
b0 4
b10110 1
0/
12
1&
#13400
0&
#13500
0-
1.
b11000 '
1*
1(
1&
#13600
0&
#13700
0.
b11001 '
0*
0(
1+
0,
0-
b11000 1
b1100000010111 3
1/
b10 4
05
1&
#13800
0&
#13900
b11001 '
0*
0(
1&
#14000
0&
1%
#14100
b11001 '
0*
0(
1&
#14200
0&
#14300
1-
0+
1.
1,
b11001 '
1*
1(
1&
#14400
0&
#14500
0.
0,
b11010 '
0*
0(
1-
0+
b1100000011001 3
b1 4
10
15
b11001 1
1/
02
1&
#14600
0&
#14700
b11010 '
0*
0(
1&
#14800
0&
#14900
b11010 '
0*
0(
1&
#15000
b1 "
b1 7
b1 8
0&
1#
#15100
0-
1.
b11010 '
1*
0(
1&
#15200
0&
#15300
1+
1,
b11011 '
0*
1(
0.
0-
b1101000011001 3
b11 4
00
05
1&
#15400
0&
#15500
1-
1.
b11011 '
1*
1(
0+
b11010 1
12
1/
10
b10 4
1&
#15600
0&
#15700
0,
b11100 '
1*
0(
0-
0+
b1101000011011 3
b1 4
10
15
b11011 1
1/
02
1&
#15800
0&
#15900
b11101 '
0*
0(
0.
05
00
b11 4
b1110000011011 3
1&
#16000
0&
0%
#16100
1+
1,
b11101 '
1*
1(
1&
#16200
0&
#16300
b11101 '
1*
1(
1-
0+
1.
b11100 1
12
1/
10
b10 4
1&
#16400
0&
#16500
0.
0,
b11110 '
0*
0(
1-
0+
b1110000011101 3
b1 4
10
15
b11101 1
1/
02
1&
#16600
0&
#16700
b11110 '
0*
0(
1&
#16800
0&
#16900
1+
1,
b11110 '
0*
1(
1&
#17000
0&
#17100
0-
1.
b11110 '
1*
0(
0,
b11100 1
12
0/
b0 4
1&
#17200
0&
#17300
0+
1,
b11111 '
1*
1(
1-
b11110 1
b1111000011101 3
1/
b10 4
05
1&
#17400
0&
#17500
0.
b100000 '
0*
1(
1-
1+
15
b11111 1
02
1/
10
b1 4
b1111000011111 3
1&
#17600
0&
#17700
b100000 '
0*
1(
0,
1+
b0 4
b11110 1
0/
12
1&
#17800
0&
#17900
0-
1.
b100000 '
1*
0(
1&
#18000
0&
1%
#18100
0+
1,
b100001 '
1*
1(
1-
b100000 1
b10000000011111 3
1/
b10 4
05
1&
#18200
0&
#18300
b100010 '
1*
1(
0-
1+
15
b100001 1
02
1/
10
b1 4
b10000000100001 3
1&
#18400
0&
#18500
0.
0,
b100011 '
0*
0(
0-
1+
b10001000100001 3
b10 4
10
05
b100010 1
1/
12
1&
#18600
0&
#18700
0+
1,
b100011 '
0*
1(
1&
#18800
0&
#18900
1-
1.
b100011 '
1*
0(
0,
0+
b0 4
b100001 1
0/
02
1&
#19000
0&
#19100
1+
0.
1,
b100100 '
0*
1(
1-
15
1/
10
b1 4
b100011 1
b10001000100011 3
1&
#19200
0&
#19300
b100100 '
0*
0(
0,
1+
b0 4
b100010 1
0/
12
1&
#19400
0&
#19500
0-
1.
b100100 '
1*
0(
1&
#19600
0&
#19700
b100101 '
1*
0(
1-
b100100 1
b10010000100011 3
1/
b10 4
05
1&
#19800
0&
#19900
b100110 '
0*
0(
0.
15
00
b11 4
b10010000100101 3
1&
#20000
0&
0%
0#
#20100
b100110 '
1*
0(
1&
#20200
0&
#20300
0+
1,
b100110 '
1*
1(
1&
#20400
0&
#20500
0,
b100110 '
1*
0(
0-
1.
0+
10
b1 4
b100101 1
02
1&
#20600
0&
#20700
1+
1,
b100111 '
1*
1(
0.
05
00
b11 4
b10011000100101 3
1&
#20800
0&
#20900
0,
b100111 '
1*
0(
1-
1.
1+
10
b10 4
b100110 1
12
1&
#21000
0&
#21100
b101000 '
0*
0(
0.
15
00
b11 4
b10011000100111 3
1&
#21200
0&
#21300
b101000 '
0*
0(
1&
#21400
0&
#21500
0+
1,
b101000 '
0*
1(
1&
#21600
0&
#21700
0-
1.
0,
b101000 '
1*
0(
0+
10
b1 4
b100111 1
02
1&
#21800
0&
#21900
1+
1,
b101001 '
0*
1(
0.
05
00
b11 4
b10100000100111 3
1&
#22000
0&
1%
#22100
1-
1.
0,
b101001 '
1*
0(
1+
10
b10 4
b101000 1
12
1&
#22200
0&
#22300
0+
1,
b101010 '
0*
1(
0.
15
00
b11 4
b10100000101001 3
1&
#22400
0&
#22500
0-
1.
0,
b101010 '
1*
0(
0+
10
b1 4
b101001 1
02
1&
#22600
0&
#22700
1+
1,
b101011 '
0*
1(
0.
05
00
b11 4
b10101000101001 3
1&
#22800
0&
#22900
1-
1.
b101011 '
1*
1(
0+
10
b10 4
b101010 1
12
1&
#23000
0&
#23100
0.
b101100 '
0*
1(
1-
1+
15
b101011 1
02
1/
10
b1 4
b10101000101011 3
1&
#23200
0&
#23300
0-
1.
b101100 '
1*
1(
0,
1+
b0 4
b101010 1
0/
12
1&
#23400
0&
#23500
0.
b101101 '
0*
0(
1+
0-
0,
05
1/
10
b10 4
b101100 1
b10110000101011 3
1&
#23600
0&
#23700
1-
0+
1.
1,
b101101 '
1*
1(
1&
#23800
0&
#23900
0,
b101110 '
1*
0(
0-
0+
15
b101101 1
02
1/
10
b1 4
b10110000101101 3
1&
#24000
0&
0%
#24100
1+
1,
b101111 '
0*
1(
0.
0-
b10111000101101 3
b11 4
00
05
1&
#24200
0&
#24300
1-
1.
b101111 '
1*
1(
0+
b101110 1
12
1/
10
b10 4
1&
#24400
0&
#24500
0.
0,
b110000 '
0*
0(
1-
0+
b10111000101111 3
b1 4
10
15
b101111 1
1/
02
1&
#24600
0&
#24700
b110000 '
0*
0(
1&
#24800
0&
#24900
b110000 '
0*
0(
1&
#25000
b10 "
b10 7
b10 8
0&
1#
#25100
0-
1.
b110000 '
1*
0(
1&
#25200
0&
#25300
1+
1,
b110001 '
0*
1(
0.
0-
b11000000101111 3
b11 4
00
05
1&
#25400
0&
#25500
b110001 '
0*
1(
0+
b110000 1
12
1/
10
b10 4
1&
#25600
0&
#25700
b110001 '
0*
1(
0,
0+
b0 4
b101111 1
0/
02
1&
#25800
0&
#25900
1-
1.
b110001 '
1*
0(
1&
#26000
0&
1%
#26100
0.
b110010 '
0*
0(
1-
b110001 1
b11000000110001 3
1/
b1 4
15
1&
#26200
0&
#26300
b110010 '
0*
0(
1&
#26400
0&
#26500
1+
1,
b110010 '
0*
1(
1&
#26600
0&
#26700
0-
1.
b110010 '
1*
1(
0,
b110000 1
12
0/
b0 4
1&
#26800
0&
#26900
0.
b110011 '
0*
1(
0+
1,
0-
b110010 1
b11001000110001 3
1/
b10 4
05
1&
#27000
0&
#27100
b110011 '
0*
0(
0,
b110001 1
02
0/
b0 4
1&
#27200
0&
#27300
1-
1.
b110011 '
1*
1(
1&
#27400
0&
#27500
0.
b110100 '
0*
0(
0+
1-
0,
15
1/
10
b1 4
b110011 1
b11001000110011 3
1&
#27600
0&
#27700
1+
1,
b110100 '
0*
1(
1&
#27800
0&
#27900
b110100 '
0*
0(
0,
b110010 1
12
0/
b0 4
1&
#28000
0&
0%
#28100
0-
1.
b110100 '
1*
1(
1&
#28200
0&
#28300
0.
b110101 '
0*
1(
0+
0-
1,
05
1/
10
b10 4
b110100 1
b11010000110011 3
1&
#28400
0&
#28500
b110101 '
0*
1(
0,
0+
b0 4
b110011 1
0/
02
1&
#28600
0&
#28700
1-
1.
b110101 '
1*
1(
1&
#28800
0&
#28900
0.
b110110 '
0*
0(
0+
0,
1-
b110101 1
b11010000110101 3
1/
b1 4
15
1&
#29000
0&
#29100
0-
1+
1.
1,
b110110 '
1*
1(
1&
#29200
0&
#29300
0.
0,
b110111 '
0*
0(
0-
1+
b11011000110101 3
b10 4
10
05
b110110 1
1/
12
1&
#29400
0&
#29500
b110111 '
0*
0(
1&
#29600
0&
#29700
1-
0+
1.
1,
b110111 '
1*
1(
1&
#29800
0&
#29900
0.
0,
b111000 '
0*
0(
1-
0+
15
b110111 1
02
1/
10
b1 4
b11011000110111 3
1&
#30000
0&
1%
0#
#30100
b111000 '
0*
0(
1&
$comment Dump file limit (10240 bytes) exceeded. $end
